Metadata-Version: 2.1
Name: Mensajes-OniNicole
Version: 6.0
Summary: Un paquete para saludar y despedir
Home-page: https://test.pypi.org/user/OniNicole/
Author: OniNicole
Author-email: nico_meli_99@gmail.com
Classifier: Environment :: Console
Classifier: Intended Audience :: Developers
Classifier: License :: OSI Approved :: MIT License
Classifier: Operating System :: OS Independent
Classifier: Operating System :: Microsoft :: Windows :: Windows 10
Classifier: Programming Language :: Python
Classifier: Programming Language :: Python :: 3.11
Classifier: Topic :: Utilities
License-File: LICENSE
Requires-Dist: numpy (>=1.23.0)
